LICENSE.txt
MANIFEST.in
README.md
setup.py
analytracks/__init__.py
analytracks/multitrack.py
analytracks/track.py
analytracks.egg-info/PKG-INFO
analytracks.egg-info/SOURCES.txt
analytracks.egg-info/dependency_links.txt
analytracks.egg-info/requires.txt
analytracks.egg-info/top_level.txt
analytracks.egg-info/zip-safe
analytracks/data/googleElevationApi(copy).key